text_to_vector/__init__.py
text_to_vector/main.py
texttovector-2025.5.180916.dist-info/licenses/LICENSE
texttovector-2025.5.180916.dist-info/METADATA
texttovector-2025.5.180916.dist-info/WHEEL
texttovector-2025.5.180916.dist-info/top_level.txt
texttovector-2025.5.180916.dist-info/RECORD
